.gitignore
CHANGES.txt
MANIFEST.in
README.md
README.txt
setup.cfg
setup.py
pyramid_osiris/__init__.py
pyramid_osiris/tests.py
pyramid_osiris.egg-info/PKG-INFO
pyramid_osiris.egg-info/SOURCES.txt
pyramid_osiris.egg-info/dependency_links.txt
pyramid_osiris.egg-info/entry_points.txt
pyramid_osiris.egg-info/not-zip-safe
pyramid_osiris.egg-info/requires.txt
pyramid_osiris.egg-info/top_level.txt