Metadata-Version: 1.1
Name: pyramid-osiris
Version: 1.0
Summary: pyramid_osiris
Home-page: https://github.com/sneridagh/pyramid_osiris
Author: Victor Fernandez de Alba
Author-email: sneridagh@gmail.com
License: UNKNOWN
Keywords: web pyramid pylons
Platform: UNKNOWN
Classifier: Programming Language :: Python
Classifier: Framework :: Pyramid
Classifier: Topic :: Internet :: WWW/HTTP
Classifier: Topic :: Internet :: WWW/HTTP :: WSGI :: Application
